Workbook

Sheet Summary
A1: Household Finance Dashboard
A2: Use the Expenses tab for daily spending and the Investments tab for contributions and current values. All figures are linked to your logs.
A3: Selected Year | B3: ='Monthly Summary'!B3 | J3: Advanced Analytics
J4: Investment Type | K4: Amount Invested (₹) | L4: Current Value (₹) | M4: Gain / Loss (₹)
A5: Expenses this year | B5: ='Monthly Summary'!B18 | C5: Invested this year | D5: ='Monthly Summary'!F18 | E5: Current investment value | F5: =SUM(Investments!$H$5:$H$1004) | G5: Investment gain / loss | H5: =SUM(Investments!$I$5:$I$1004) | J5: Stocks | K5: =SUMIFS(Investments!$G$5:$G$1004,Investments!$D$5:$D$1004,J5) | L5: =SUMIFS(Investments!$H$5:$H$1004,Investments!$D$5:$D$1004,J5) | M5: =L5-K5
J6: Mutual Funds | K6: =SUMIFS(Investments!$G$5:$G$1004,Investments!$D$5:$D$1004,J6) | L6: =SUMIFS(Investments!$H$5:$H$1004,Investments!$D$5:$D$1004,J6) | M6: =L6-K6
J7: ETF | K7: =SUMIFS(Investments!$G$5:$G$1004,Investments!$D$5:$D$1004,J7) | L7: =SUMIFS(Investments!$H$5:$H$1004,Investments!$D$5:$D$1004,J7) | M7: =L7-K7
A8: Yearly expense breakdown by category | J8: Fixed Deposit | K8: =SUMIFS(Investments!$G$5:$G$1004,Investments!$D$5:$D$1004,J8) | L8: =SUMIFS(Investments!$H$5:$H$1004,Investments!$D$5:$D$1004,J8) | M8: =L8-K8
A9: Category | B9: Total (₹) | C9: Category | D9: Total (₹) | E9: Owner | F9: Expenses (₹) | G9: Owner | H9: Invested (₹) | J9: PPF | K9: =SUMIFS(Investments!$G$5:$G$1004,Investments!$D$5:$D$1004,J9) | L9: =SUMIFS(Investments!$H$5:$H$1004,Investments!$D$5:$D$1004,J9) | M9: =L9-K9
A10: =IF(Lists!$A5="","",Lists!$A5) | B10: =IF($A10="","",SUMIFS(Expenses!$F$5:$F$1004,Expenses!$D$5:$D$1004,$A10,Expenses!$A$5:$A$1004,">="&DATE($B$3,1,1),Expenses!$A$5:$A$1004,"<"&DATE($B$3+1,1,1))) | E10: Me | F10: =SUMIFS(Expenses!$F$5:$F$1004,Expenses!$C$5:$C$1004,E10,Expenses!$A$5:$A$1004,">="&DATE($B$3,1,1),Expenses!$A$5:$A$1004,"<"&DATE($B$3+1,1,1)) | G10: Me | H10: =SUMIFS(Investments!$G$5:$G$1004,Investments!$C$5:$C$1004,G10,Investments!$A$5:$A$1004,">="&DATE($B$3,1,1),Investments!$A$5:$A$1004,"<"&DATE($B$3+1,1,1)) | J10: EPF | K10: =SUMIFS(Investments!$G$5:$G$1004,Investments!$D$5:$D$1004,J10) | L10: =SUMIFS(Investments!$H$5:$H$1004,Investments!$D$5:$D$1004,J10) | M10: =L10-K10
A11: =IF(Lists!$A6="","",Lists!$A6) | B11: =IF($A11="","",SUMIFS(Expenses!$F$5:$F$1004,Expenses!$D$5:$D$1004,$A11,Expenses!$A$5:$A$1004,">="&DATE($B$3,1,1),Expenses!$A$5:$A$1004,"<"&DATE($B$3+1,1,1))) | E11: Husband | F11: =SUMIFS(Expenses!$F$5:$F$1004,Expenses!$C$5:$C$1004,E11,Expenses!$A$5:$A$1004,">="&DATE($B$3,1,1),Expenses!$A$5:$A$1004,"<"&DATE($B$3+1,1,1)) | G11: Husband | H11: =SUMIFS(Investments!$G$5:$G$1004,Investments!$C$5:$C$1004,G11,Investments!$A$5:$A$1004,">="&DATE($B$3,1,1),Investments!$A$5:$A$1004,"<"&DATE($B$3+1,1,1)) | J11: NPS | K11: =SUMIFS(Investments!$G$5:$G$1004,Investments!$D$5:$D$1004,J11) | L11: =SUMIFS(Investments!$H$5:$H$1004,Investments!$D$5:$D$1004,J11) | M11: =L11-K11
A12: =IF(Lists!$A7="","",Lists!$A7) | B12: =IF($A12="","",SUMIFS(Expenses!$F$5:$F$1004,Expenses!$D$5:$D$1004,$A12,Expenses!$A$5:$A$1004,">="&DATE($B$3,1,1),Expenses!$A$5:$A$1004,"<"&DATE($B$3+1,1,1))) | E12: Joint | F12: =SUMIFS(Expenses!$F$5:$F$1004,Expenses!$C$5:$C$1004,E12,Expenses!$A$5:$A$1004,">="&DATE($B$3,1,1),Expenses!$A$5:$A$1004,"<"&DATE($B$3+1,1,1)) | G12: Joint | H12: =SUMIFS(Investments!$G$5:$G$1004,Investments!$C$5:$C$1004,G12,Investments!$A$5:$A$1004,">="&DATE($B$3,1,1),Investments!$A$5:$A$1004,"<"&DATE($B$3+1,1,1)) | J12: Gold | K12: =SUMIFS(Investments!$G$5:$G$1004,Investments!$D$5:$D$1004,J12) | L12: =SUMIFS(Investments!$H$5:$H$1004,Investments!$D$5:$D$1004,J12) | M12: =L12-K12
A13: =IF(Lists!$A8="","",Lists!$A8) | B13: =IF($A13="","",SUMIFS(Expenses!$F$5:$F$1004,Expenses!$D$5:$D$1004,$A13,Expenses!$A$5:$A$1004,">="&DATE($B$3,1,1),Expenses!$A$5:$A$1004,"<"&DATE($B$3+1,1,1))) | J13: Bonds | K13: =SUMIFS(Investments!$G$5:$G$1004,Investments!$D$5:$D$1004,J13) | L13: =SUMIFS(Investments!$H$5:$H$1004,Investments!$D$5:$D$1004,J13) | M13: =L13-K13
A14: =IF(Lists!$A9="","",Lists!$A9) | B14: =IF($A14="","",SUMIFS(Expenses!$F$5:$F$1004,Expenses!$D$5:$D$1004,$A14,Expenses!$A$5:$A$1004,">="&DATE($B$3,1,1),Expenses!$A$5:$A$1004,"<"&DATE($B$3+1,1,1))) | J14: SIP | K14: =SUMIFS(Investments!$G$5:$G$1004,Investments!$D$5:$D$1004,J14) | L14: =SUMIFS(Investments!$H$5:$H$1004,Investments!$D$5:$D$1004,J14) | M14: =L14-K14
A15: =IF(Lists!$A10="","",Lists!$A10) | B15: =IF($A15="","",SUMIFS(Expenses!$F$5:$F$1004,Expenses!$D$5:$D$1004,$A15,Expenses!$A$5:$A$1004,">="&DATE($B$3,1,1),Expenses!$A$5:$A$1004,"<"&DATE($B$3+1,1,1))) | D15: Monthly trend | J15: Real Estate | K15: =SUMIFS(Investments!$G$5:$G$1004,Investments!$D$5:$D$1004,J15) | L15: =SUMIFS(Investments!$H$5:$H$1004,Investments!$D$5:$D$1004,J15) | M15: =L15-K15
A16: =IF(Lists!$A11="","",Lists!$A11) | B16: =IF($A16="","",SUMIFS(Expenses!$F$5:$F$1004,Expenses!$D$5:$D$1004,$A16,Expenses!$A$5:$A$1004,">="&DATE($B$3,1,1),Expenses!$A$5:$A$1004,"<"&DATE($B$3+1,1,1))) | D16: Month | E16: Expenses (₹) | F16: Invested (₹) | J16: Other | K16: =SUMIFS(Investments!$G$5:$G$1004,Investments!$D$5:$D$1004,J16) | L16: =SUMIFS(Investments!$H$5:$H$1004,Investments!$D$5:$D$1004,J16) | M16: =L16-K16
A17: =IF(Lists!$A12="","",Lists!$A12) | B17: =IF($A17="","",SUMIFS(Expenses!$F$5:$F$1004,Expenses!$D$5:$D$1004,$A17,Expenses!$A$5:$A$1004,">="&DATE($B$3,1,1),Expenses!$A$5:$A$1004,"<"&DATE($B$3+1,1,1))) | D17: ='Monthly Summary'!A6 | E17: ='Monthly Summary'!B6 | F17: ='Monthly Summary'!F6
A18: =IF(Lists!$A13="","",Lists!$A13) | B18: =IF($A18="","",SUMIFS(Expenses!$F$5:$F$1004,Expenses!$D$5:$D$1004,$A18,Expenses!$A$5:$A$1004,">="&DATE($B$3,1,1),Expenses!$A$5:$A$1004,"<"&DATE($B$3+1,1,1))) | D18: ='Monthly Summary'!A7 | E18: ='Monthly Summary'!B7 | F18: ='Monthly Summary'!F7
A19: =IF(Lists!$A14="","",Lists!$A14) | B19: =IF($A19="","",SUMIFS(Expenses!$F$5:$F$1004,Expenses!$D$5:$D$1004,$A19,Expenses!$A$5:$A$1004,">="&DATE($B$3,1,1),Expenses!$A$5:$A$1004,"<"&DATE($B$3+1,1,1))) | D19: ='Monthly Summary'!A8 | E19: ='Monthly Summary'!B8 | F19: ='Monthly Summary'!F8 | J19: Owner | K19: Amount Invested (₹) | L19: Current Value (₹)
A20: =IF(Lists!$A15="","",Lists!$A15) | B20: =IF($A20="","",SUMIFS(Expenses!$F$5:$F$1004,Expenses!$D$5:$D$1004,$A20,Expenses!$A$5:$A$1004,">="&DATE($B$3,1,1),Expenses!$A$5:$A$1004,"<"&DATE($B$3+1,1,1))) | D20: ='Monthly Summary'!A9 | E20: ='Monthly Summary'!B9 | F20: ='Monthly Summary'!F9 | J20: Me | K20: =SUMIFS(Investments!$G$5:$G$1004,Investments!$C$5:$C$1004,J20) | L20: =SUMIFS(Investments!$H$5:$H$1004,Investments!$C$5:$C$1004,J20)
A21: =IF(Lists!$A16="","",Lists!$A16) | B21: =IF($A21="","",SUMIFS(Expenses!$F$5:$F$1004,Expenses!$D$5:$D$1004,$A21,Expenses!$A$5:$A$1004,">="&DATE($B$3,1,1),Expenses!$A$5:$A$1004,"<"&DATE($B$3+1,1,1))) | D21: ='Monthly Summary'!A10 | E21: ='Monthly Summary'!B10 | F21: ='Monthly Summary'!F10 | J21: Husband | K21: =SUMIFS(Investments!$G$5:$G$1004,Investments!$C$5:$C$1004,J21) | L21: =SUMIFS(Investments!$H$5:$H$1004,Investments!$C$5:$C$1004,J21)
A22: =IF(Lists!$A17="","",Lists!$A17) | B22: =IF($A22="","",SUMIFS(Expenses!$F$5:$F$1004,Expenses!$D$5:$D$1004,$A22,Expenses!$A$5:$A$1004,">="&DATE($B$3,1,1),Expenses!$A$5:$A$1004,"<"&DATE($B$3+1,1,1))) | D22: ='Monthly Summary'!A11 | E22: ='Monthly Summary'!B11 | F22: ='Monthly Summary'!F11 | J22: Joint | K22: =SUMIFS(Investments!$G$5:$G$1004,Investments!$C$5:$C$1004,J22) | L22: =SUMIFS(Investments!$H$5:$H$1004,Investments!$C$5:$C$1004,J22)
A23: =IF(Lists!$A18="","",Lists!$A18) | B23: =IF($A23="","",SUMIFS(Expenses!$F$5:$F$1004,Expenses!$D$5:$D$1004,$A23,Expenses!$A$5:$A$1004,">="&DATE($B$3,1,1),Expenses!$A$5:$A$1004,"<"&DATE($B$3+1,1,1))) | D23: ='Monthly Summary'!A12 | E23: ='Monthly Summary'!B12 | F23: ='Monthly Summary'!F12
A24: =IF(Lists!$A19="","",Lists!$A19) | B24: =IF($A24="","",SUMIFS(Expenses!$F$5:$F$1004,Expenses!$D$5:$D$1004,$A24,Expenses!$A$5:$A$1004,">="&DATE($B$3,1,1),Expenses!$A$5:$A$1004,"<"&DATE($B$3+1,1,1))) | D24: ='Monthly Summary'!A13 | E24: ='Monthly Summary'!B13 | F24: ='Monthly Summary'!F13
A25: =IF(Lists!$A20="","",Lists!$A20) | B25: =IF($A25="","",SUMIFS(Expenses!$F$5:$F$1004,Expenses!$D$5:$D$1004,$A25,Expenses!$A$5:$A$1004,">="&DATE($B$3,1,1),Expenses!$A$5:$A$1004,"<"&DATE($B$3+1,1,1))) | D25: ='Monthly Summary'!A14 | E25: ='Monthly Summary'!B14 | F25: ='Monthly Summary'!F14
A26: =IF(Lists!$A21="","",Lists!$A21) | B26: =IF($A26="","",SUMIFS(Expenses!$F$5:$F$1004,Expenses!$D$5:$D$1004,$A26,Expenses!$A$5:$A$1004,">="&DATE($B$3,1,1),Expenses!$A$5:$A$1004,"<"&DATE($B$3+1,1,1))) | D26: ='Monthly Summary'!A15 | E26: ='Monthly Summary'!B15 | F26: ='Monthly Summary'!F15
A27: =IF(Lists!$A22="","",Lists!$A22) | B27: =IF($A27="","",SUMIFS(Expenses!$F$5:$F$1004,Expenses!$D$5:$D$1004,$A27,Expenses!$A$5:$A$1004,">="&DATE($B$3,1,1),Expenses!$A$5:$A$1004,"<"&DATE($B$3+1,1,1))) | D27: ='Monthly Summary'!A16 | E27: ='Monthly Summary'!B16 | F27: ='Monthly Summary'!F16
A28: =IF(Lists!$A23="","",Lists!$A23) | B28: =IF($A28="","",SUMIFS(Expenses!$F$5:$F$1004,Expenses!$D$5:$D$1004,$A28,Expenses!$A$5:$A$1004,">="&DATE($B$3,1,1),Expenses!$A$5:$A$1004,"<"&DATE($B$3+1,1,1))) | D28: ='Monthly Summary'!A17 | E28: ='Monthly Summary'!B17 | F28: ='Monthly Summary'!F17
A29: =IF(Lists!$A24="","",Lists!$A24) | B29: =IF($A29="","",SUMIFS(Expenses!$F$5:$F$1004,Expenses!$D$5:$D$1004,$A29,Expenses!$A$5:$A$1004,">="&DATE($B$3,1,1),Expenses!$A$5:$A$1004,"<"&DATE($B$3+1,1,1)))
A31: How to read this dashboard
A32: All charts are linked to the daily logs. Select a year in Monthly Summary!B3 to update year-based expense and monthly views. Investment allocation uses the current values entered in the Investments tab. Update current values periodically; market prices are not fetched automatically.
A35: Income & Savings (Selected Year)
A36: Income this year | B36: ='Monthly Summary'!$K$18 | C36: Expenses this year | D36: ='Monthly Summary'!$B$18 | E36: Savings this year | F36: =B36-D36 | G36: Savings rate | H36: =IF(B36=0,"",F36/B36)
A38: Net Worth (latest balance snapshot)
A39: As on | B39: =IF(Balances!$I$1="","",Balances!$I$1) | C39: Bank + Cash | D39: =Balances!$I$5 | E39: Investments | F39: =Balances!$I$7 | G39: Loans / Liab. | H39: =Balances!$I$8
A40: Total Assets | B40: =Balances!$I$5+Balances!$I$6+Balances!$I$7 | C40: Net Worth | D40: =Balances!$I$9
A42: Net Worth Component | B42: Value (₹)
A43: Bank + Cash | B43: =Balances!$I$5
A44: Other Assets | B44: =Balances!$I$6
A45: Investments | B45: =Balances!$I$7

Sheet Expenses
A1: Daily Expense Log
A2: Enter one transaction per row. Use positive amounts; choose who paid and whether it was shared. Summary tabs update from these entries.
A4: Date | B4: Month (auto) | C4: Paid By | D4: Category | E4: Description / Merchant | F4: Amount (₹) | G4: Payment Method | H4: Shared? | I4: Notes | J4: Year (auto)
B5: =IF(A5="","",DATE(YEAR(A5),MONTH(A5),1)) | J5: =IF(A5="","",YEAR(A5))
B6: =IF(A6="","",DATE(YEAR(A6),MONTH(A6),1)) | J6: =IF(A6="","",YEAR(A6))
B7: =IF(A7="","",DATE(YEAR(A7),MONTH(A7),1)) | J7: =IF(A7="","",YEAR(A7))
B8: =IF(A8="","",DATE(YEAR(A8),MONTH(A8),1)) | J8: =IF(A8="","",YEAR(A8))
B9: =IF(A9="","",DATE(YEAR(A9),MONTH(A9),1)) | J9: =IF(A9="","",YEAR(A9))
B10: =IF(A10="","",DATE(YEAR(A10),MONTH(A10),1)) | J10: =IF(A10="","",YEAR(A10))
B11: =IF(A11="","",DATE(YEAR(A11),MONTH(A11),1)) | J11: =IF(A11="","",YEAR(A11))
B12: =IF(A12="","",DATE(YEAR(A12),MONTH(A12),1)) | J12: =IF(A12="","",YEAR(A12))
B13: =IF(A13="","",DATE(YEAR(A13),MONTH(A13),1)) | J13: =IF(A13="","",YEAR(A13))
B14: =IF(A14="","",DATE(YEAR(A14),MONTH(A14),1)) | J14: =IF(A14="","",YEAR(A14))
B15: =IF(A15="","",DATE(YEAR(A15),MONTH(A15),1)) | J15: =IF(A15="","",YEAR(A15))
B16: =IF(A16="","",DATE(YEAR(A16),MONTH(A16),1)) | J16: =IF(A16="","",YEAR(A16))
... B1004: =IF(A1004="","",DATE(YEAR(A1004),MONTH(A1004),1)) | J1004: =IF(A1004="","",YEAR(A1004))

Sheet Investments
A1: Investment Tracker
A2: Record contributions/purchases and current value snapshots. One row per investment entry or valuation update. Summary totals use the latest values you enter in the Current Value column.
A4: Date | B4: Month (auto) | C4: Owner | D4: Investment Type | E4: Investment / Asset Name | F4: Account / Platform | G4: Amount Invested (₹) | H4: Current Value (₹) | I4: Gain / Loss (₹ auto) | J4: Notes
B5: =IF(A5="","",DATE(YEAR(A5),MONTH(A5),1)) | I5: =IF(OR(G5="",H5=""),"",H5-G5)
B6: =IF(A6="","",DATE(YEAR(A6),MONTH(A6),1)) | I6: =IF(OR(G6="",H6=""),"",H6-G6)
B7: =IF(A7="","",DATE(YEAR(A7),MONTH(A7),1)) | I7: =IF(OR(G7="",H7=""),"",H7-G7)
B8: =IF(A8="","",DATE(YEAR(A8),MONTH(A8),1)) | I8: =IF(OR(G8="",H8=""),"",H8-G8)
B9: =IF(A9="","",DATE(YEAR(A9),MONTH(A9),1)) | I9: =IF(OR(G9="",H9=""),"",H9-G9)
B10: =IF(A10="","",DATE(YEAR(A10),MONTH(A10),1)) | I10: =IF(OR(G10="",H10=""),"",H10-G10)
B11: =IF(A11="","",DATE(YEAR(A11),MONTH(A11),1)) | I11: =IF(OR(G11="",H11=""),"",H11-G11)
B12: =IF(A12="","",DATE(YEAR(A12),MONTH(A12),1)) | I12: =IF(OR(G12="",H12=""),"",H12-G12)
B13: =IF(A13="","",DATE(YEAR(A13),MONTH(A13),1)) | I13: =IF(OR(G13="",H13=""),"",H13-G13)
B14: =IF(A14="","",DATE(YEAR(A14),MONTH(A14),1)) | I14: =IF(OR(G14="",H14=""),"",H14-G14)
B15: =IF(A15="","",DATE(YEAR(A15),MONTH(A15),1)) | I15: =IF(OR(G15="",H15=""),"",H15-G15)
B16: =IF(A16="","",DATE(YEAR(A16),MONTH(A16),1)) | I16: =IF(OR(G16="",H16=""),"",H16-G16)
... B1004: =IF(A1004="","",DATE(YEAR(A1004),MONTH(A1004),1)) | I1004: =IF(OR(G1004="",H1004=""),"",H1004-G1004)

Sheet Income
A1: Income Log
A2: Record every income received -- salary (usually once a month), plus bonuses, interest, dividends, rent, refunds, etc. One row per receipt. The Monthly Summary and dashboard roll these up automatically.
A4: Date | B4: Month (auto) | C4: Earner | D4: Income Type | E4: Description / Source | F4: Amount (₹) | G4: Received In | H4: Notes | I4: Year (auto)
B5: =IF(A5="","",DATE(YEAR(A5),MONTH(A5),1)) | I5: =IF(A5="","",YEAR(A5))
B6: =IF(A6="","",DATE(YEAR(A6),MONTH(A6),1)) | I6: =IF(A6="","",YEAR(A6))
B7: =IF(A7="","",DATE(YEAR(A7),MONTH(A7),1)) | I7: =IF(A7="","",YEAR(A7))
B8: =IF(A8="","",DATE(YEAR(A8),MONTH(A8),1)) | I8: =IF(A8="","",YEAR(A8))
B9: =IF(A9="","",DATE(YEAR(A9),MONTH(A9),1)) | I9: =IF(A9="","",YEAR(A9))
B10: =IF(A10="","",DATE(YEAR(A10),MONTH(A10),1)) | I10: =IF(A10="","",YEAR(A10))
B11: =IF(A11="","",DATE(YEAR(A11),MONTH(A11),1)) | I11: =IF(A11="","",YEAR(A11))
B12: =IF(A12="","",DATE(YEAR(A12),MONTH(A12),1)) | I12: =IF(A12="","",YEAR(A12))
B13: =IF(A13="","",DATE(YEAR(A13),MONTH(A13),1)) | I13: =IF(A13="","",YEAR(A13))
B14: =IF(A14="","",DATE(YEAR(A14),MONTH(A14),1)) | I14: =IF(A14="","",YEAR(A14))
B15: =IF(A15="","",DATE(YEAR(A15),MONTH(A15),1)) | I15: =IF(A15="","",YEAR(A15))
B16: =IF(A16="","",DATE(YEAR(A16),MONTH(A16),1)) | I16: =IF(A16="","",YEAR(A16))
... B1004: =IF(A1004="","",DATE(YEAR(A1004),MONTH(A1004),1)) | I1004: =IF(A1004="","",YEAR(A1004))

Sheet Balances
A1: Balances & Net Worth Snapshots | H1: Latest snapshot date | I1: =IF(COUNT(A5:A504)=0,"",MAX(A5:A504))
A2: Periodically record the balance of each bank/cash account and any loans. Enter LOANS and CREDIT-CARD dues as NEGATIVE amounts. Net worth below uses the most recent snapshot date plus the current value of your Investments.
H3: Net Worth Summary
A4: As-on Date | B4: Owner | C4: Account Type | D4: Account / Institution | E4: Balance (₹) | F4: Notes | H4: Component | I4: Value (₹)
H5: Bank + Cash | I5: =SUMIFS($E$5:$E$504,$C$5:$C$504,"Bank Account",$A$5:$A$504,$I$1)+SUMIFS($E$5:$E$504,$C$5:$C$504,"Savings Account",$A$5:$A$504,$I$1)+SUMIFS($E$5:$E$504,$C$5:$C$504,"Cash",$A$5:$A$504,$I$1)
H6: Other Assets | I6: =SUMIFS($E$5:$E$504,$C$5:$C$504,"Other Asset",$A$5:$A$504,$I$1)
H7: Investments (current value) | I7: =SUM(Investments!$H$5:$H$1004)
H8: Loans / Liabilities | I8: =SUMIFS($E$5:$E$504,$C$5:$C$504,"Loan (Liability)",$A$5:$A$504,$I$1)+SUMIFS($E$5:$E$504,$C$5:$C$504,"Credit Card (Liability)",$A$5:$A$504,$I$1)
H9: Net Worth | I9: =I5+I6+I7+I8

Sheet Monthly Summary
A1: Monthly Summary
A2: Change the year in B3. Monthly totals are calculated from the Expenses and Investments tabs.
A3: Year | B3: 2026
A5: Month | B5: Total Expenses (₹) | C5: Your Expenses (₹) | D5: Husband's Expenses (₹) | E5: Joint Expenses (₹) | F5: Invested (₹) | G5: Your Investments (₹) | H5: Husband's Investments (₹) | I5: Monthly Gain/Loss (₹) | J5: Current Value Added (₹) | K5: Income (₹) | L5: Your Income (₹) | M5: Husband's Income (₹) | N5: Savings (₹) | O5: Savings Rate
A6: =DATE($B$3,1,1) | B6: =SUMIFS(Expenses!$F$5:$F$1004,Expenses!$A$5:$A$1004,">="&$A6,Expenses!$A$5:$A$1004,"<"&EDATE($A6,1)) | C6: =SUMIFS(Expenses!$F$5:$F$1004,Expenses!$A$5:$A$1004,">="&$A6,Expenses!$A$5:$A$1004,"<"&EDATE($A6,1),Expenses!$C$5:$C$1004,"Me") | D6: =SUMIFS(Expenses!$F$5:$F$1004,Expenses!$A$5:$A$1004,">="&$A6,Expenses!$A$5:$A$1004,"<"&EDATE($A6,1),Expenses!$C$5:$C$1004,"Husband") | E6: =SUMIFS(Expenses!$F$5:$F$1004,Expenses!$A$5:$A$1004,">="&$A6,Expenses!$A$5:$A$1004,"<"&EDATE($A6,1),Expenses!$C$5:$C$1004,"Joint") | F6: =SUMIFS(Investments!$G$5:$G$1004,Investments!$A$5:$A$1004,">="&$A6,Investments!$A$5:$A$1004,"<"&EDATE($A6,1)) | G6: =SUMIFS(Investments!$G$5:$G$1004,Investments!$A$5:$A$1004,">="&$A6,Investments!$A$5:$A$1004,"<"&EDATE($A6,1),Investments!$C$5:$C$1004,"Me") | H6: =SUMIFS(Investments!$G$5:$G$1004,Investments!$A$5:$A$1004,">="&$A6,Investments!$A$5:$A$1004,"<"&EDATE($A6,1),Investments!$C$5:$C$1004,"Husband") | I6: =SUMIFS(Investments!$I$5:$I$1004,Investments!$A$5:$A$1004,">="&$A6,Investments!$A$5:$A$1004,"<"&EDATE($A6,1)) | J6: =SUMIFS(Investments!$H$5:$H$1004,Investments!$A$5:$A$1004,">="&$A6,Investments!$A$5:$A$1004,"<"&EDATE($A6,1)) | K6: =SUMIFS(Income!$F$5:$F$1004,Income!$A$5:$A$1004,">="&$A6,Income!$A$5:$A$1004,"<"&EDATE($A6,1)) | L6: =SUMIFS(Income!$F$5:$F$1004,Income!$A$5:$A$1004,">="&$A6,Income!$A$5:$A$1004,"<"&EDATE($A6,1),Income!$C$5:$C$1004,"Me") | M6: =SUMIFS(Income!$F$5:$F$1004,Income!$A$5:$A$1004,">="&$A6,Income!$A$5:$A$1004,"<"&EDATE($A6,1),Income!$C$5:$C$1004,"Husband") | N6: =K6-B6 | O6: =IF(K6=0,"",N6/K6)
A7: =DATE($B$3,2,1) | B7: =SUMIFS(Expenses!$F$5:$F$1004,Expenses!$A$5:$A$1004,">="&$A7,Expenses!$A$5:$A$1004,"<"&EDATE($A7,1)) | C7: =SUMIFS(Expenses!$F$5:$F$1004,Expenses!$A$5:$A$1004,">="&$A7,Expenses!$A$5:$A$1004,"<"&EDATE($A7,1),Expenses!$C$5:$C$1004,"Me") | D7: =SUMIFS(Expenses!$F$5:$F$1004,Expenses!$A$5:$A$1004,">="&$A7,Expenses!$A$5:$A$1004,"<"&EDATE($A7,1),Expenses!$C$5:$C$1004,"Husband") | E7: =SUMIFS(Expenses!$F$5:$F$1004,Expenses!$A$5:$A$1004,">="&$A7,Expenses!$A$5:$A$1004,"<"&EDATE($A7,1),Expenses!$C$5:$C$1004,"Joint") | F7: =SUMIFS(Investments!$G$5:$G$1004,Investments!$A$5:$A$1004,">="&$A7,Investments!$A$5:$A$1004,"<"&EDATE($A7,1)) | G7: =SUMIFS(Investments!$G$5:$G$1004,Investments!$A$5:$A$1004,">="&$A7,Investments!$A$5:$A$1004,"<"&EDATE($A7,1),Investments!$C$5:$C$1004,"Me") | H7: =SUMIFS(Investments!$G$5:$G$1004,Investments!$A$5:$A$1004,">="&$A7,Investments!$A$5:$A$1004,"<"&EDATE($A7,1),Investments!$C$5:$C$1004,"Husband") | I7: =SUMIFS(Investments!$I$5:$I$1004,Investments!$A$5:$A$1004,">="&$A7,Investments!$A$5:$A$1004,"<"&EDATE($A7,1)) | J7: =SUMIFS(Investments!$H$5:$H$1004,Investments!$A$5:$A$1004,">="&$A7,Investments!$A$5:$A$1004,"<"&EDATE($A7,1)) | K7: =SUMIFS(Income!$F$5:$F$1004,Income!$A$5:$A$1004,">="&$A7,Income!$A$5:$A$1004,"<"&EDATE($A7,1)) | L7: =SUMIFS(Income!$F$5:$F$1004,Income!$A$5:$A$1004,">="&$A7,Income!$A$5:$A$1004,"<"&EDATE($A7,1),Income!$C$5:$C$1004,"Me") | M7: =SUMIFS(Income!$F$5:$F$1004,Income!$A$5:$A$1004,">="&$A7,Income!$A$5:$A$1004,"<"&EDATE($A7,1),Income!$C$5:$C$1004,"Husband") | N7: =K7-B7 | O7: =IF(K7=0,"",N7/K7)
A8: =DATE($B$3,3,1) | B8: =SUMIFS(Expenses!$F$5:$F$1004,Expenses!$A$5:$A$1004,">="&$A8,Expenses!$A$5:$A$1004,"<"&EDATE($A8,1)) | C8: =SUMIFS(Expenses!$F$5:$F$1004,Expenses!$A$5:$A$1004,">="&$A8,Expenses!$A$5:$A$1004,"<"&EDATE($A8,1),Expenses!$C$5:$C$1004,"Me") | D8: =SUMIFS(Expenses!$F$5:$F$1004,Expenses!$A$5:$A$1004,">="&$A8,Expenses!$A$5:$A$1004,"<"&EDATE($A8,1),Expenses!$C$5:$C$1004,"Husband") | E8: =SUMIFS(Expenses!$F$5:$F$1004,Expenses!$A$5:$A$1004,">="&$A8,Expenses!$A$5:$A$1004,"<"&EDATE($A8,1),Expenses!$C$5:$C$1004,"Joint") | F8: =SUMIFS(Investments!$G$5:$G$1004,Investments!$A$5:$A$1004,">="&$A8,Investments!$A$5:$A$1004,"<"&EDATE($A8,1)) | G8: =SUMIFS(Investments!$G$5:$G$1004,Investments!$A$5:$A$1004,">="&$A8,Investments!$A$5:$A$1004,"<"&EDATE($A8,1),Investments!$C$5:$C$1004,"Me") | H8: =SUMIFS(Investments!$G$5:$G$1004,Investments!$A$5:$A$1004,">="&$A8,Investments!$A$5:$A$1004,"<"&EDATE($A8,1),Investments!$C$5:$C$1004,"Husband") | I8: =SUMIFS(Investments!$I$5:$I$1004,Investments!$A$5:$A$1004,">="&$A8,Investments!$A$5:$A$1004,"<"&EDATE($A8,1)) | J8: =SUMIFS(Investments!$H$5:$H$1004,Investments!$A$5:$A$1004,">="&$A8,Investments!$A$5:$A$1004,"<"&EDATE($A8,1)) | K8: =SUMIFS(Income!$F$5:$F$1004,Income!$A$5:$A$1004,">="&$A8,Income!$A$5:$A$1004,"<"&EDATE($A8,1)) | L8: =SUMIFS(Income!$F$5:$F$1004,Income!$A$5:$A$1004,">="&$A8,Income!$A$5:$A$1004,"<"&EDATE($A8,1),Income!$C$5:$C$1004,"Me") | M8: =SUMIFS(Income!$F$5:$F$1004,Income!$A$5:$A$1004,">="&$A8,Income!$A$5:$A$1004,"<"&EDATE($A8,1),Income!$C$5:$C$1004,"Husband") | N8: =K8-B8 | O8: =IF(K8=0,"",N8/K8)
A9: =DATE($B$3,4,1) | B9: =SUMIFS(Expenses!$F$5:$F$1004,Expenses!$A$5:$A$1004,">="&$A9,Expenses!$A$5:$A$1004,"<"&EDATE($A9,1)) | C9: =SUMIFS(Expenses!$F$5:$F$1004,Expenses!$A$5:$A$1004,">="&$A9,Expenses!$A$5:$A$1004,"<"&EDATE($A9,1),Expenses!$C$5:$C$1004,"Me") | D9: =SUMIFS(Expenses!$F$5:$F$1004,Expenses!$A$5:$A$1004,">="&$A9,Expenses!$A$5:$A$1004,"<"&EDATE($A9,1),Expenses!$C$5:$C$1004,"Husband") | E9: =SUMIFS(Expenses!$F$5:$F$1004,Expenses!$A$5:$A$1004,">="&$A9,Expenses!$A$5:$A$1004,"<"&EDATE($A9,1),Expenses!$C$5:$C$1004,"Joint") | F9: =SUMIFS(Investments!$G$5:$G$1004,Investments!$A$5:$A$1004,">="&$A9,Investments!$A$5:$A$1004,"<"&EDATE($A9,1)) | G9: =SUMIFS(Investments!$G$5:$G$1004,Investments!$A$5:$A$1004,">="&$A9,Investments!$A$5:$A$1004,"<"&EDATE($A9,1),Investments!$C$5:$C$1004,"Me") | H9: =SUMIFS(Investments!$G$5:$G$1004,Investments!$A$5:$A$1004,">="&$A9,Investments!$A$5:$A$1004,"<"&EDATE($A9,1),Investments!$C$5:$C$1004,"Husband") | I9: =SUMIFS(Investments!$I$5:$I$1004,Investments!$A$5:$A$1004,">="&$A9,Investments!$A$5:$A$1004,"<"&EDATE($A9,1)) | J9: =SUMIFS(Investments!$H$5:$H$1004,Investments!$A$5:$A$1004,">="&$A9,Investments!$A$5:$A$1004,"<"&EDATE($A9,1)) | K9: =SUMIFS(Income!$F$5:$F$1004,Income!$A$5:$A$1004,">="&$A9,Income!$A$5:$A$1004,"<"&EDATE($A9,1)) | L9: =SUMIFS(Income!$F$5:$F$1004,Income!$A$5:$A$1004,">="&$A9,Income!$A$5:$A$1004,"<"&EDATE($A9,1),Income!$C$5:$C$1004,"Me") | M9: =SUMIFS(Income!$F$5:$F$1004,Income!$A$5:$A$1004,">="&$A9,Income!$A$5:$A$1004,"<"&EDATE($A9,1),Income!$C$5:$C$1004,"Husband") | N9: =K9-B9 | O9: =IF(K9=0,"",N9/K9)
A10: =DATE($B$3,5,1) | B10: =SUMIFS(Expenses!$F$5:$F$1004,Expenses!$A$5:$A$1004,">="&$A10,Expenses!$A$5:$A$1004,"<"&EDATE($A10,1)) | C10: =SUMIFS(Expenses!$F$5:$F$1004,Expenses!$A$5:$A$1004,">="&$A10,Expenses!$A$5:$A$1004,"<"&EDATE($A10,1),Expenses!$C$5:$C$1004,"Me") | D10: =SUMIFS(Expenses!$F$5:$F$1004,Expenses!$A$5:$A$1004,">="&$A10,Expenses!$A$5:$A$1004,"<"&EDATE($A10,1),Expenses!$C$5:$C$1004,"Husband") | E10: =SUMIFS(Expenses!$F$5:$F$1004,Expenses!$A$5:$A$1004,">="&$A10,Expenses!$A$5:$A$1004,"<"&EDATE($A10,1),Expenses!$C$5:$C$1004,"Joint") | F10: =SUMIFS(Investments!$G$5:$G$1004,Investments!$A$5:$A$1004,">="&$A10,Investments!$A$5:$A$1004,"<"&EDATE($A10,1)) | G10: =SUMIFS(Investments!$G$5:$G$1004,Investments!$A$5:$A$1004,">="&$A10,Investments!$A$5:$A$1004,"<"&EDATE($A10,1),Investments!$C$5:$C$1004,"Me") | H10: =SUMIFS(Investments!$G$5:$G$1004,Investments!$A$5:$A$1004,">="&$A10,Investments!$A$5:$A$1004,"<"&EDATE($A10,1),Investments!$C$5:$C$1004,"Husband") | I10: =SUMIFS(Investments!$I$5:$I$1004,Investments!$A$5:$A$1004,">="&$A10,Investments!$A$5:$A$1004,"<"&EDATE($A10,1)) | J10: =SUMIFS(Investments!$H$5:$H$1004,Investments!$A$5:$A$1004,">="&$A10,Investments!$A$5:$A$1004,"<"&EDATE($A10,1)) | K10: =SUMIFS(Income!$F$5:$F$1004,Income!$A$5:$A$1004,">="&$A10,Income!$A$5:$A$1004,"<"&EDATE($A10,1)) | L10: =SUMIFS(Income!$F$5:$F$1004,Income!$A$5:$A$1004,">="&$A10,Income!$A$5:$A$1004,"<"&EDATE($A10,1),Income!$C$5:$C$1004,"Me") | M10: =SUMIFS(Income!$F$5:$F$1004,Income!$A$5:$A$1004,">="&$A10,Income!$A$5:$A$1004,"<"&EDATE($A10,1),Income!$C$5:$C$1004,"Husband") | N10: =K10-B10 | O10: =IF(K10=0,"",N10/K10)
A11: =DATE($B$3,6,1) | B11: =SUMIFS(Expenses!$F$5:$F$1004,Expenses!$A$5:$A$1004,">="&$A11,Expenses!$A$5:$A$1004,"<"&EDATE($A11,1)) | C11: =SUMIFS(Expenses!$F$5:$F$1004,Expenses!$A$5:$A$1004,">="&$A11,Expenses!$A$5:$A$1004,"<"&EDATE($A11,1),Expenses!$C$5:$C$1004,"Me") | D11: =SUMIFS(Expenses!$F$5:$F$1004,Expenses!$A$5:$A$1004,">="&$A11,Expenses!$A$5:$A$1004,"<"&EDATE($A11,1),Expenses!$C$5:$C$1004,"Husband") | E11: =SUMIFS(Expenses!$F$5:$F$1004,Expenses!$A$5:$A$1004,">="&$A11,Expenses!$A$5:$A$1004,"<"&EDATE($A11,1),Expenses!$C$5:$C$1004,"Joint") | F11: =SUMIFS(Investments!$G$5:$G$1004,Investments!$A$5:$A$1004,">="&$A11,Investments!$A$5:$A$1004,"<"&EDATE($A11,1)) | G11: =SUMIFS(Investments!$G$5:$G$1004,Investments!$A$5:$A$1004,">="&$A11,Investments!$A$5:$A$1004,"<"&EDATE($A11,1),Investments!$C$5:$C$1004,"Me") | H11: =SUMIFS(Investments!$G$5:$G$1004,Investments!$A$5:$A$1004,">="&$A11,Investments!$A$5:$A$1004,"<"&EDATE($A11,1),Investments!$C$5:$C$1004,"Husband") | I11: =SUMIFS(Investments!$I$5:$I$1004,Investments!$A$5:$A$1004,">="&$A11,Investments!$A$5:$A$1004,"<"&EDATE($A11,1)) | J11: =SUMIFS(Investments!$H$5:$H$1004,Investments!$A$5:$A$1004,">="&$A11,Investments!$A$5:$A$1004,"<"&EDATE($A11,1)) | K11: =SUMIFS(Income!$F$5:$F$1004,Income!$A$5:$A$1004,">="&$A11,Income!$A$5:$A$1004,"<"&EDATE($A11,1)) | L11: =SUMIFS(Income!$F$5:$F$1004,Income!$A$5:$A$1004,">="&$A11,Income!$A$5:$A$1004,"<"&EDATE($A11,1),Income!$C$5:$C$1004,"Me") | M11: =SUMIFS(Income!$F$5:$F$1004,Income!$A$5:$A$1004,">="&$A11,Income!$A$5:$A$1004,"<"&EDATE($A11,1),Income!$C$5:$C$1004,"Husband") | N11: =K11-B11 | O11: =IF(K11=0,"",N11/K11)
A12: =DATE($B$3,7,1) | B12: =SUMIFS(Expenses!$F$5:$F$1004,Expenses!$A$5:$A$1004,">="&$A12,Expenses!$A$5:$A$1004,"<"&EDATE($A12,1)) | C12: =SUMIFS(Expenses!$F$5:$F$1004,Expenses!$A$5:$A$1004,">="&$A12,Expenses!$A$5:$A$1004,"<"&EDATE($A12,1),Expenses!$C$5:$C$1004,"Me") | D12: =SUMIFS(Expenses!$F$5:$F$1004,Expenses!$A$5:$A$1004,">="&$A12,Expenses!$A$5:$A$1004,"<"&EDATE($A12,1),Expenses!$C$5:$C$1004,"Husband") | E12: =SUMIFS(Expenses!$F$5:$F$1004,Expenses!$A$5:$A$1004,">="&$A12,Expenses!$A$5:$A$1004,"<"&EDATE($A12,1),Expenses!$C$5:$C$1004,"Joint") | F12: =SUMIFS(Investments!$G$5:$G$1004,Investments!$A$5:$A$1004,">="&$A12,Investments!$A$5:$A$1004,"<"&EDATE($A12,1)) | G12: =SUMIFS(Investments!$G$5:$G$1004,Investments!$A$5:$A$1004,">="&$A12,Investments!$A$5:$A$1004,"<"&EDATE($A12,1),Investments!$C$5:$C$1004,"Me") | H12: =SUMIFS(Investments!$G$5:$G$1004,Investments!$A$5:$A$1004,">="&$A12,Investments!$A$5:$A$1004,"<"&EDATE($A12,1),Investments!$C$5:$C$1004,"Husband") | I12: =SUMIFS(Investments!$I$5:$I$1004,Investments!$A$5:$A$1004,">="&$A12,Investments!$A$5:$A$1004,"<"&EDATE($A12,1)) | J12: =SUMIFS(Investments!$H$5:$H$1004,Investments!$A$5:$A$1004,">="&$A12,Investments!$A$5:$A$1004,"<"&EDATE($A12,1)) | K12: =SUMIFS(Income!$F$5:$F$1004,Income!$A$5:$A$1004,">="&$A12,Income!$A$5:$A$1004,"<"&EDATE($A12,1)) | L12: =SUMIFS(Income!$F$5:$F$1004,Income!$A$5:$A$1004,">="&$A12,Income!$A$5:$A$1004,"<"&EDATE($A12,1),Income!$C$5:$C$1004,"Me") | M12: =SUMIFS(Income!$F$5:$F$1004,Income!$A$5:$A$1004,">="&$A12,Income!$A$5:$A$1004,"<"&EDATE($A12,1),Income!$C$5:$C$1004,"Husband") | N12: =K12-B12 | O12: =IF(K12=0,"",N12/K12)
A13: =DATE($B$3,8,1) | B13: =SUMIFS(Expenses!$F$5:$F$1004,Expenses!$A$5:$A$1004,">="&$A13,Expenses!$A$5:$A$1004,"<"&EDATE($A13,1)) | C13: =SUMIFS(Expenses!$F$5:$F$1004,Expenses!$A$5:$A$1004,">="&$A13,Expenses!$A$5:$A$1004,"<"&EDATE($A13,1),Expenses!$C$5:$C$1004,"Me") | D13: =SUMIFS(Expenses!$F$5:$F$1004,Expenses!$A$5:$A$1004,">="&$A13,Expenses!$A$5:$A$1004,"<"&EDATE($A13,1),Expenses!$C$5:$C$1004,"Husband") | E13: =SUMIFS(Expenses!$F$5:$F$1004,Expenses!$A$5:$A$1004,">="&$A13,Expenses!$A$5:$A$1004,"<"&EDATE($A13,1),Expenses!$C$5:$C$1004,"Joint") | F13: =SUMIFS(Investments!$G$5:$G$1004,Investments!$A$5:$A$1004,">="&$A13,Investments!$A$5:$A$1004,"<"&EDATE($A13,1)) | G13: =SUMIFS(Investments!$G$5:$G$1004,Investments!$A$5:$A$1004,">="&$A13,Investments!$A$5:$A$1004,"<"&EDATE($A13,1),Investments!$C$5:$C$1004,"Me") | H13: =SUMIFS(Investments!$G$5:$G$1004,Investments!$A$5:$A$1004,">="&$A13,Investments!$A$5:$A$1004,"<"&EDATE($A13,1),Investments!$C$5:$C$1004,"Husband") | I13: =SUMIFS(Investments!$I$5:$I$1004,Investments!$A$5:$A$1004,">="&$A13,Investments!$A$5:$A$1004,"<"&EDATE($A13,1)) | J13: =SUMIFS(Investments!$H$5:$H$1004,Investments!$A$5:$A$1004,">="&$A13,Investments!$A$5:$A$1004,"<"&EDATE($A13,1)) | K13: =SUMIFS(Income!$F$5:$F$1004,Income!$A$5:$A$1004,">="&$A13,Income!$A$5:$A$1004,"<"&EDATE($A13,1)) | L13: =SUMIFS(Income!$F$5:$F$1004,Income!$A$5:$A$1004,">="&$A13,Income!$A$5:$A$1004,"<"&EDATE($A13,1),Income!$C$5:$C$1004,"Me") | M13: =SUMIFS(Income!$F$5:$F$1004,Income!$A$5:$A$1004,">="&$A13,Income!$A$5:$A$1004,"<"&EDATE($A13,1),Income!$C$5:$C$1004,"Husband") | N13: =K13-B13 | O13: =IF(K13=0,"",N13/K13)
A14: =DATE($B$3,9,1) | B14: =SUMIFS(Expenses!$F$5:$F$1004,Expenses!$A$5:$A$1004,">="&$A14,Expenses!$A$5:$A$1004,"<"&EDATE($A14,1)) | C14: =SUMIFS(Expenses!$F$5:$F$1004,Expenses!$A$5:$A$1004,">="&$A14,Expenses!$A$5:$A$1004,"<"&EDATE($A14,1),Expenses!$C$5:$C$1004,"Me") | D14: =SUMIFS(Expenses!$F$5:$F$1004,Expenses!$A$5:$A$1004,">="&$A14,Expenses!$A$5:$A$1004,"<"&EDATE($A14,1),Expenses!$C$5:$C$1004,"Husband") | E14: =SUMIFS(Expenses!$F$5:$F$1004,Expenses!$A$5:$A$1004,">="&$A14,Expenses!$A$5:$A$1004,"<"&EDATE($A14,1),Expenses!$C$5:$C$1004,"Joint") | F14: =SUMIFS(Investments!$G$5:$G$1004,Investments!$A$5:$A$1004,">="&$A14,Investments!$A$5:$A$1004,"<"&EDATE($A14,1)) | G14: =SUMIFS(Investments!$G$5:$G$1004,Investments!$A$5:$A$1004,">="&$A14,Investments!$A$5:$A$1004,"<"&EDATE($A14,1),Investments!$C$5:$C$1004,"Me") | H14: =SUMIFS(Investments!$G$5:$G$1004,Investments!$A$5:$A$1004,">="&$A14,Investments!$A$5:$A$1004,"<"&EDATE($A14,1),Investments!$C$5:$C$1004,"Husband") | I14: =SUMIFS(Investments!$I$5:$I$1004,Investments!$A$5:$A$1004,">="&$A14,Investments!$A$5:$A$1004,"<"&EDATE($A14,1)) | J14: =SUMIFS(Investments!$H$5:$H$1004,Investments!$A$5:$A$1004,">="&$A14,Investments!$A$5:$A$1004,"<"&EDATE($A14,1)) | K14: =SUMIFS(Income!$F$5:$F$1004,Income!$A$5:$A$1004,">="&$A14,Income!$A$5:$A$1004,"<"&EDATE($A14,1)) | L14: =SUMIFS(Income!$F$5:$F$1004,Income!$A$5:$A$1004,">="&$A14,Income!$A$5:$A$1004,"<"&EDATE($A14,1),Income!$C$5:$C$1004,"Me") | M14: =SUMIFS(Income!$F$5:$F$1004,Income!$A$5:$A$1004,">="&$A14,Income!$A$5:$A$1004,"<"&EDATE($A14,1),Income!$C$5:$C$1004,"Husband") | N14: =K14-B14 | O14: =IF(K14=0,"",N14/K14)
A15: =DATE($B$3,10,1) | B15: =SUMIFS(Expenses!$F$5:$F$1004,Expenses!$A$5:$A$1004,">="&$A15,Expenses!$A$5:$A$1004,"<"&EDATE($A15,1)) | C15: =SUMIFS(Expenses!$F$5:$F$1004,Expenses!$A$5:$A$1004,">="&$A15,Expenses!$A$5:$A$1004,"<"&EDATE($A15,1),Expenses!$C$5:$C$1004,"Me") | D15: =SUMIFS(Expenses!$F$5:$F$1004,Expenses!$A$5:$A$1004,">="&$A15,Expenses!$A$5:$A$1004,"<"&EDATE($A15,1),Expenses!$C$5:$C$1004,"Husband") | E15: =SUMIFS(Expenses!$F$5:$F$1004,Expenses!$A$5:$A$1004,">="&$A15,Expenses!$A$5:$A$1004,"<"&EDATE($A15,1),Expenses!$C$5:$C$1004,"Joint") | F15: =SUMIFS(Investments!$G$5:$G$1004,Investments!$A$5:$A$1004,">="&$A15,Investments!$A$5:$A$1004,"<"&EDATE($A15,1)) | G15: =SUMIFS(Investments!$G$5:$G$1004,Investments!$A$5:$A$1004,">="&$A15,Investments!$A$5:$A$1004,"<"&EDATE($A15,1),Investments!$C$5:$C$1004,"Me") | H15: =SUMIFS(Investments!$G$5:$G$1004,Investments!$A$5:$A$1004,">="&$A15,Investments!$A$5:$A$1004,"<"&EDATE($A15,1),Investments!$C$5:$C$1004,"Husband") | I15: =SUMIFS(Investments!$I$5:$I$1004,Investments!$A$5:$A$1004,">="&$A15,Investments!$A$5:$A$1004,"<"&EDATE($A15,1)) | J15: =SUMIFS(Investments!$H$5:$H$1004,Investments!$A$5:$A$1004,">="&$A15,Investments!$A$5:$A$1004,"<"&EDATE($A15,1)) | K15: =SUMIFS(Income!$F$5:$F$1004,Income!$A$5:$A$1004,">="&$A15,Income!$A$5:$A$1004,"<"&EDATE($A15,1)) | L15: =SUMIFS(Income!$F$5:$F$1004,Income!$A$5:$A$1004,">="&$A15,Income!$A$5:$A$1004,"<"&EDATE($A15,1),Income!$C$5:$C$1004,"Me") | M15: =SUMIFS(Income!$F$5:$F$1004,Income!$A$5:$A$1004,">="&$A15,Income!$A$5:$A$1004,"<"&EDATE($A15,1),Income!$C$5:$C$1004,"Husband") | N15: =K15-B15 | O15: =IF(K15=0,"",N15/K15)
A16: =DATE($B$3,11,1) | B16: =SUMIFS(Expenses!$F$5:$F$1004,Expenses!$A$5:$A$1004,">="&$A16,Expenses!$A$5:$A$1004,"<"&EDATE($A16,1)) | C16: =SUMIFS(Expenses!$F$5:$F$1004,Expenses!$A$5:$A$1004,">="&$A16,Expenses!$A$5:$A$1004,"<"&EDATE($A16,1),Expenses!$C$5:$C$1004,"Me") | D16: =SUMIFS(Expenses!$F$5:$F$1004,Expenses!$A$5:$A$1004,">="&$A16,Expenses!$A$5:$A$1004,"<"&EDATE($A16,1),Expenses!$C$5:$C$1004,"Husband") | E16: =SUMIFS(Expenses!$F$5:$F$1004,Expenses!$A$5:$A$1004,">="&$A16,Expenses!$A$5:$A$1004,"<"&EDATE($A16,1),Expenses!$C$5:$C$1004,"Joint") | F16: =SUMIFS(Investments!$G$5:$G$1004,Investments!$A$5:$A$1004,">="&$A16,Investments!$A$5:$A$1004,"<"&EDATE($A16,1)) | G16: =SUMIFS(Investments!$G$5:$G$1004,Investments!$A$5:$A$1004,">="&$A16,Investments!$A$5:$A$1004,"<"&EDATE($A16,1),Investments!$C$5:$C$1004,"Me") | H16: =SUMIFS(Investments!$G$5:$G$1004,Investments!$A$5:$A$1004,">="&$A16,Investments!$A$5:$A$1004,"<"&EDATE($A16,1),Investments!$C$5:$C$1004,"Husband") | I16: =SUMIFS(Investments!$I$5:$I$1004,Investments!$A$5:$A$1004,">="&$A16,Investments!$A$5:$A$1004,"<"&EDATE($A16,1)) | J16: =SUMIFS(Investments!$H$5:$H$1004,Investments!$A$5:$A$1004,">="&$A16,Investments!$A$5:$A$1004,"<"&EDATE($A16,1)) | K16: =SUMIFS(Income!$F$5:$F$1004,Income!$A$5:$A$1004,">="&$A16,Income!$A$5:$A$1004,"<"&EDATE($A16,1)) | L16: =SUMIFS(Income!$F$5:$F$1004,Income!$A$5:$A$1004,">="&$A16,Income!$A$5:$A$1004,"<"&EDATE($A16,1),Income!$C$5:$C$1004,"Me") | M16: =SUMIFS(Income!$F$5:$F$1004,Income!$A$5:$A$1004,">="&$A16,Income!$A$5:$A$1004,"<"&EDATE($A16,1),Income!$C$5:$C$1004,"Husband") | N16: =K16-B16 | O16: =IF(K16=0,"",N16/K16)
A17: =DATE($B$3,12,1) | B17: =SUMIFS(Expenses!$F$5:$F$1004,Expenses!$A$5:$A$1004,">="&$A17,Expenses!$A$5:$A$1004,"<"&EDATE($A17,1)) | C17: =SUMIFS(Expenses!$F$5:$F$1004,Expenses!$A$5:$A$1004,">="&$A17,Expenses!$A$5:$A$1004,"<"&EDATE($A17,1),Expenses!$C$5:$C$1004,"Me") | D17: =SUMIFS(Expenses!$F$5:$F$1004,Expenses!$A$5:$A$1004,">="&$A17,Expenses!$A$5:$A$1004,"<"&EDATE($A17,1),Expenses!$C$5:$C$1004,"Husband") | E17: =SUMIFS(Expenses!$F$5:$F$1004,Expenses!$A$5:$A$1004,">="&$A17,Expenses!$A$5:$A$1004,"<"&EDATE($A17,1),Expenses!$C$5:$C$1004,"Joint") | F17: =SUMIFS(Investments!$G$5:$G$1004,Investments!$A$5:$A$1004,">="&$A17,Investments!$A$5:$A$1004,"<"&EDATE($A17,1)) | G17: =SUMIFS(Investments!$G$5:$G$1004,Investments!$A$5:$A$1004,">="&$A17,Investments!$A$5:$A$1004,"<"&EDATE($A17,1),Investments!$C$5:$C$1004,"Me") | H17: =SUMIFS(Investments!$G$5:$G$1004,Investments!$A$5:$A$1004,">="&$A17,Investments!$A$5:$A$1004,"<"&EDATE($A17,1),Investments!$C$5:$C$1004,"Husband") | I17: =SUMIFS(Investments!$I$5:$I$1004,Investments!$A$5:$A$1004,">="&$A17,Investments!$A$5:$A$1004,"<"&EDATE($A17,1)) | J17: =SUMIFS(Investments!$H$5:$H$1004,Investments!$A$5:$A$1004,">="&$A17,Investments!$A$5:$A$1004,"<"&EDATE($A17,1)) | K17: =SUMIFS(Income!$F$5:$F$1004,Income!$A$5:$A$1004,">="&$A17,Income!$A$5:$A$1004,"<"&EDATE($A17,1)) | L17: =SUMIFS(Income!$F$5:$F$1004,Income!$A$5:$A$1004,">="&$A17,Income!$A$5:$A$1004,"<"&EDATE($A17,1),Income!$C$5:$C$1004,"Me") | M17: =SUMIFS(Income!$F$5:$F$1004,Income!$A$5:$A$1004,">="&$A17,Income!$A$5:$A$1004,"<"&EDATE($A17,1),Income!$C$5:$C$1004,"Husband") | N17: =K17-B17 | O17: =IF(K17=0,"",N17/K17)
A18: Year Total | B18: =SUM(B6:B17) | C18: =SUM(C6:C17) | D18: =SUM(D6:D17) | E18: =SUM(E6:E17) | F18: =SUM(F6:F17) | G18: =SUM(G6:G17) | H18: =SUM(H6:H17) | I18: =SUM(I6:I17) | ... N18: =SUM(N6:N17) | O18: =IF(K18=0,"",N18/K18)

Sheet Lists
A1: Lists & Categories
A2: Edit these lists to customize the dropdowns used in the tracker.
A4: Expense Categories | B4: Payment Methods | C4: People | D4: Investment Types | E4: Accounts | F4: Income Types | G4: Account / Balance Types | I4: Quick Guide
A5: Rent | B5: UPI | C5: Me | D5: Stocks | E5: Bank Account | F5: Salary | G5: Bank Account | I5: 1. Log every expense (daily) in Expenses and every investment in Investments.
A6: Groceries | B6: Credit Card | C6: Husband | D6: Mutual Funds | E6: Cash | F6: Bonus / Variable Pay | G6: Savings Account | I6: 2. Log income in the Income tab -- salary monthly, plus any ad-hoc income.
A7: Utilities - Electricity/Water | B7: Debit Card | C7: Joint | D7: ETF | E7: Credit Card | F7: Business / Profession | G7: Cash | I7: 3. Record bank balances & loans periodically in Balances (one dated snapshot).
A8: Wi-Fi / Internet | B8: Cash | D8: Fixed Deposit | E8: Brokerage | F8: Freelance / Side Income | G8: Other Asset | I8: 4. For loans/credit-card dues in Balances, enter the amount as a NEGATIVE number.
A9: Mobile / Phone | B9: Bank Transfer | D9: PPF | E9: Mutual Fund Platform | F9: Rental Income | G9: Loan (Liability) | I9: 5. Keep Owner / Category / Type values consistent with these dropdown lists.
A10: Eating Out | B10: Auto-debit | D10: EPF | E10: EPF/PPF/NPS | F10: Interest Income | G10: Credit Card (Liability) | I10: 6. Add new categories here -- dropdowns & summaries pick them up automatically.
A11: Transport / Fuel | B11: Other | D11: NPS | E11: Other | F11: Dividend Income | I11: 7. Enter Current Value per investment holding; do not duplicate holdings.
A12: Household Supplies | D12: Gold | F12: Capital Gains | I12: 8. Pick the year in Monthly Summary!B3 to refresh all year-based views.
A13: Healthcare | D13: Bonds | F13: Gift Received
A14: Shopping / Personal | D14: SIP | F14: Refund / Reimbursement
A15: Festivals / Celebrations | D15: Real Estate | F15: Other
A16: Gifting | D16: Other
A17: Travel / Vacation
A18: Education / Courses
A19: Subscriptions
A20: Insurance
A21: EMI / Loan
A22: Child / Family
A23: Pet Expenses
A24: Other
